[
  {
    "id": "0pkg7j",
    "url": "https://w.wallhaven.cc/full/0p/wallhaven-0pkg7j.jpg",
    "thumb": "https://th.wallhaven.cc/orig/0p/0pkg7j.jpg"
  },
  {
    "id": "4y1m9x",
    "url": "https://w.wallhaven.cc/full/4y/wallhaven-4y1m9x.jpg",
    "thumb": "https://th.wallhaven.cc/orig/4y/4y1m9x.jpg"
  },
  {
    "id": "4xd5q3",
    "url": "https://w.wallhaven.cc/full/4x/wallhaven-4xd5q3.jpg",
    "thumb": "https://th.wallhaven.cc/orig/4x/4xd5q3.jpg"
  },
  {
    "id": "mpddvk",
    "url": "https://w.wallhaven.cc/full/mp/wallhaven-mpddvk.jpg",
    "thumb": "https://th.wallhaven.cc/orig/mp/mpddvk.jpg"
  },
  {
    "id": "4gd1ge",
    "url": "https://w.wallhaven.cc/full/4g/wallhaven-4gd1ge.jpg",
    "thumb": "https://th.wallhaven.cc/orig/4g/4gd1ge.jpg"
  },
  {
    "id": "3lym3y",
    "url": "https://w.wallhaven.cc/full/3l/wallhaven-3lym3y.png",
    "thumb": "https://th.wallhaven.cc/orig/3l/3lym3y.jpg"
  },
  {
    "id": "xllzmv",
    "url": "https://w.wallhaven.cc/full/xl/wallhaven-xllzmv.jpg",
    "thumb": "https://th.wallhaven.cc/orig/xl/xllzmv.jpg"
  },
  {
    "id": "4xgzpl",
    "url": "https://w.wallhaven.cc/full/4x/wallhaven-4xgzpl.jpg",
    "thumb": "https://th.wallhaven.cc/orig/4x/4xgzpl.jpg"
  },
  {
    "id": "4glm37",
    "url": "https://w.wallhaven.cc/full/4g/wallhaven-4glm37.jpg",
    "thumb": "https://th.wallhaven.cc/orig/4g/4glm37.jpg"
  },
  {
    "id": "od38v9",
    "url": "https://w.wallhaven.cc/full/od/wallhaven-od38v9.jpg",
    "thumb": "https://th.wallhaven.cc/orig/od/od38v9.jpg"
  }
]