[
  {
    "id": "x11wg3",
    "url": "https://w.wallhaven.cc/full/x1/wallhaven-x11wg3.jpg",
    "thumb": "https://th.wallhaven.cc/orig/x1/x11wg3.jpg"
  },
  {
    "id": "4vypw8",
    "url": "https://w.wallhaven.cc/full/4v/wallhaven-4vypw8.jpg",
    "thumb": "https://th.wallhaven.cc/orig/4v/4vypw8.jpg"
  },
  {
    "id": "4vvy88",
    "url": "https://w.wallhaven.cc/full/4v/wallhaven-4vvy88.jpg",
    "thumb": "https://th.wallhaven.cc/orig/4v/4vvy88.jpg"
  },
  {
    "id": "p9ogre",
    "url": "https://w.wallhaven.cc/full/p9/wallhaven-p9ogre.jpg",
    "thumb": "https://th.wallhaven.cc/orig/p9/p9ogre.jpg"
  },
  {
    "id": "4dpemg",
    "url": "https://w.wallhaven.cc/full/4d/wallhaven-4dpemg.jpg",
    "thumb": "https://th.wallhaven.cc/orig/4d/4dpemg.jpg"
  },
  {
    "id": "j3ex8m",
    "url": "https://w.wallhaven.cc/full/j3/wallhaven-j3ex8m.jpg",
    "thumb": "https://th.wallhaven.cc/orig/j3/j3ex8m.jpg"
  },
  {
    "id": "4g7mje",
    "url": "https://w.wallhaven.cc/full/4g/wallhaven-4g7mje.jpg",
    "thumb": "https://th.wallhaven.cc/orig/4g/4g7mje.jpg"
  },
  {
    "id": "9698xw",
    "url": "https://w.wallhaven.cc/full/96/wallhaven-9698xw.jpg",
    "thumb": "https://th.wallhaven.cc/orig/96/9698xw.jpg"
  },
  {
    "id": "k93roq",
    "url": "https://w.wallhaven.cc/full/k9/wallhaven-k93roq.png",
    "thumb": "https://th.wallhaven.cc/orig/k9/k93roq.jpg"
  },
  {
    "id": "eo7p28",
    "url": "https://w.wallhaven.cc/full/eo/wallhaven-eo7p28.jpg",
    "thumb": "https://th.wallhaven.cc/orig/eo/eo7p28.jpg"
  }
]