[
  {
    "id": "pklkr9",
    "url": "https://w.wallhaven.cc/full/pk/wallhaven-pklkr9.jpg",
    "thumb": "https://th.wallhaven.cc/orig/pk/pklkr9.jpg"
  },
  {
    "id": "43v67y",
    "url": "https://w.wallhaven.cc/full/43/wallhaven-43v67y.jpg",
    "thumb": "https://th.wallhaven.cc/orig/43/43v67y.jpg"
  },
  {
    "id": "e7vqyo",
    "url": "https://w.wallhaven.cc/full/e7/wallhaven-e7vqyo.jpg",
    "thumb": "https://th.wallhaven.cc/orig/e7/e7vqyo.jpg"
  },
  {
    "id": "vmvqe3",
    "url": "https://w.wallhaven.cc/full/vm/wallhaven-vmvqe3.jpg",
    "thumb": "https://th.wallhaven.cc/orig/vm/vmvqe3.jpg"
  },
  {
    "id": "578jx8",
    "url": "https://w.wallhaven.cc/full/57/wallhaven-578jx8.jpg",
    "thumb": "https://th.wallhaven.cc/orig/57/578jx8.jpg"
  },
  {
    "id": "xlgk13",
    "url": "https://w.wallhaven.cc/full/xl/wallhaven-xlgk13.jpg",
    "thumb": "https://th.wallhaven.cc/orig/xl/xlgk13.jpg"
  },
  {
    "id": "1kkdov",
    "url": "https://w.wallhaven.cc/full/1k/wallhaven-1kkdov.jpg",
    "thumb": "https://th.wallhaven.cc/orig/1k/1kkdov.jpg"
  },
  {
    "id": "yjx5dl",
    "url": "https://w.wallhaven.cc/full/yj/wallhaven-yjx5dl.jpg",
    "thumb": "https://th.wallhaven.cc/orig/yj/yjx5dl.jpg"
  },
  {
    "id": "q6geo5",
    "url": "https://w.wallhaven.cc/full/q6/wallhaven-q6geo5.png",
    "thumb": "https://th.wallhaven.cc/orig/q6/q6geo5.jpg"
  },
  {
    "id": "lmlzyp",
    "url": "https://w.wallhaven.cc/full/lm/wallhaven-lmlzyp.png",
    "thumb": "https://th.wallhaven.cc/orig/lm/lmlzyp.jpg"
  }
]