[
  {
    "id": "138dv9",
    "url": "https://w.wallhaven.cc/full/13/wallhaven-138dv9.jpg",
    "thumb": "https://th.wallhaven.cc/orig/13/138dv9.jpg"
  },
  {
    "id": "5d8eq5",
    "url": "https://w.wallhaven.cc/full/5d/wallhaven-5d8eq5.jpg",
    "thumb": "https://th.wallhaven.cc/orig/5d/5d8eq5.jpg"
  },
  {
    "id": "d5d8d3",
    "url": "https://w.wallhaven.cc/full/d5/wallhaven-d5d8d3.jpg",
    "thumb": "https://th.wallhaven.cc/orig/d5/d5d8d3.jpg"
  },
  {
    "id": "498de8",
    "url": "https://w.wallhaven.cc/full/49/wallhaven-498de8.jpg",
    "thumb": "https://th.wallhaven.cc/orig/49/498de8.jpg"
  },
  {
    "id": "eor15o",
    "url": "https://w.wallhaven.cc/full/eo/wallhaven-eor15o.png",
    "thumb": "https://th.wallhaven.cc/orig/eo/eor15o.jpg"
  },
  {
    "id": "g7kq1e",
    "url": "https://w.wallhaven.cc/full/g7/wallhaven-g7kq1e.jpg",
    "thumb": "https://th.wallhaven.cc/orig/g7/g7kq1e.jpg"
  },
  {
    "id": "l3vr7r",
    "url": "https://w.wallhaven.cc/full/l3/wallhaven-l3vr7r.jpg",
    "thumb": "https://th.wallhaven.cc/orig/l3/l3vr7r.jpg"
  },
  {
    "id": "72vj3v",
    "url": "https://w.wallhaven.cc/full/72/wallhaven-72vj3v.jpg",
    "thumb": "https://th.wallhaven.cc/orig/72/72vj3v.jpg"
  },
  {
    "id": "6oogzl",
    "url": "https://w.wallhaven.cc/full/6o/wallhaven-6oogzl.jpg",
    "thumb": "https://th.wallhaven.cc/orig/6o/6oogzl.jpg"
  },
  {
    "id": "rddyem",
    "url": "https://w.wallhaven.cc/full/rd/wallhaven-rddyem.png",
    "thumb": "https://th.wallhaven.cc/orig/rd/rddyem.jpg"
  }
]